LICENSE.txt
MANIFEST.in
README.rst
setup.py
django_actionlog/__init__.py
django_actionlog/actionlog.py
django_actionlog/middleware.py
django_actionlog/sql_logger.py
django_actionlog.egg-info/PKG-INFO
django_actionlog.egg-info/SOURCES.txt
django_actionlog.egg-info/dependency_links.txt
django_actionlog.egg-info/requires.txt
django_actionlog.egg-info/top_level.txt
django_actionlog/handler/__init__.py
django_actionlog/handler/file.py
django_actionlog/handler/fluentd.py
django_actionlog/handler/handler_manager.py
django_actionlog/handler/log_format.py
django_actionlog/handler/null.py
django_actionlog/handler/stdout.py