Metadata-Version: 1.1
Name: django-actionlog
Version: 0.9.14
Summary: You can check the python-time, sql-time and query-count for each request for Django
Home-page: http://github.com/fujimisakari/django-actionlog
Author: Ryo Fujimoto
Author-email: fujimisakari@gmail.com
License: BSD
Platform: UNKNOWN
Classifier: Development Status :: 4 - Beta
Classifier: Environment :: Web Environment
Classifier: Framework :: Django
Classifier: Intended Audience :: Developers
Classifier: License :: OSI Approved :: BSD License
Classifier: Operating System :: OS Independent
Classifier: Programming Language :: Python
Classifier: Programming Language :: Python :: 2
Classifier: Programming Language :: Python :: 2.7
Classifier: Programming Language :: Python :: 3
Classifier: Programming Language :: Python :: 3.4
Classifier: Programming Language :: Python :: 3.5
Classifier: Programming Language :: Python :: Implementation :: PyPy
Classifier: Topic :: Utilities
